automl_lite/__init__.py
automl_lite/cli/__init__.py
automl_lite/cli/__main__.py
automl_lite/cli/main.py
automl_lite/config/advanced_config.py
automl_lite/config/config_manager.py
automl_lite/core/__init__.py
automl_lite/core/automl.py
automl_lite/experiments/tracker.py
automl_lite/interpretability/advanced_interpreter.py
automl_lite/models/__init__.py
automl_lite/models/deep_learning.py
automl_lite/models/selector.py
automl_lite/models/time_series.py
automl_lite/nas/__init__.py
automl_lite/nas/architecture.py
automl_lite/nas/config_templates.py
automl_lite/nas/controller.py
automl_lite/nas/hardware_profiler.py
automl_lite/nas/logging_utils.py
automl_lite/nas/multi_objective.py
automl_lite/nas/performance_estimator.py
automl_lite/nas/repository.py
automl_lite/nas/search_space.py
automl_lite/nas/search_strategy.py
automl_lite/nas/utils.py
automl_lite/nas/validators.py
automl_lite/nas/visualization.py
automl_lite/optimization/__init__.py
automl_lite/optimization/optimizer.py
automl_lite/preprocessing/__init__.py
automl_lite/preprocessing/feature_engineering.py
automl_lite/preprocessing/pipeline.py
automl_lite/ui/interactive_dashboard.py
automl_lite/ui/terminal_ui.py
automl_lite/utils/__init__.py
automl_lite/utils/data_analyzer.py
automl_lite/utils/logger.py
automl_lite/utils/model_comparator.py
automl_lite/utils/problem_detector.py
automl_lite/utils/validators.py
automl_lite/visualization/__init__.py
automl_lite/visualization/reporter.py
automl_lite-0.2.1.dist-info/licenses/LICENSE
automl_lite-0.2.1.dist-info/METADATA
automl_lite-0.2.1.dist-info/WHEEL
automl_lite-0.2.1.dist-info/entry_points.txt
automl_lite-0.2.1.dist-info/top_level.txt
automl_lite-0.2.1.dist-info/RECORD
