Metadata-Version: 2.4
Name: automl-lite
Version: 0.2.1
Summary: A simplified automated machine learning package with Neural Architecture Search for non-experts
Author-email: Sherin Joseph Roy <connect@sherinjosephroy.link>
Maintainer-email: Sherin Joseph Roy <connect@sherinjosephroy.link>
License: MIT
Project-URL: Homepage, https://github.com/Sherin-SEF-AI/AutoML-Lite
Project-URL: Documentation, https://github.com/Sherin-SEF-AI/AutoML-Lite#readme
Project-URL: Repository, https://github.com/Sherin-SEF-AI/AutoML-Lite
Project-URL: Bug Tracker, https://github.com/Sherin-SEF-AI/AutoML-Lite/issues
Keywords: machine-learning,automl,scikit-learn,data-science,ml
Classifier: Development Status :: 4 - Beta
Classifier: Intended Audience :: Developers
Classifier: Intended Audience :: Science/Research
Classifier: License :: OSI Approved :: MIT License
Classifier: Operating System :: OS Independent
Classifier: Programming Language :: Python :: 3
Classifier: Programming Language :: Python :: 3.8
Classifier: Programming Language :: Python :: 3.9
Classifier: Programming Language :: Python :: 3.10
Classifier: Programming Language :: Python :: 3.11
Classifier: Programming Language :: Python :: 3.12
Classifier: Topic :: Scientific/Engineering :: Artificial Intelligence
Classifier: Topic :: Software Development :: Libraries :: Python Modules
Requires-Python: >=3.8
License-File: LICENSE
Requires-Dist: numpy>=1.21.0
Requires-Dist: pandas>=1.3.0
Requires-Dist: scikit-learn>=1.0.0
Requires-Dist: optuna>=3.0.0
Requires-Dist: shap>=0.41.0
Requires-Dist: matplotlib>=3.5.0
Requires-Dist: seaborn>=0.11.0
Requires-Dist: joblib>=1.1.0
Requires-Dist: plotly>=5.0.0
Requires-Dist: jinja2>=3.0.0
Requires-Dist: tqdm>=4.62.0
Requires-Dist: scipy>=1.7.0
Requires-Dist: category-encoders>=2.3.0
Requires-Dist: imbalanced-learn>=0.8.0
Provides-Extra: dev
Requires-Dist: pytest>=7.0.0; extra == "dev"
Requires-Dist: pytest-cov>=4.0.0; extra == "dev"
Requires-Dist: black>=22.0.0; extra == "dev"
Requires-Dist: isort>=5.10.0; extra == "dev"
Requires-Dist: flake8>=5.0.0; extra == "dev"
Requires-Dist: mypy>=0.991; extra == "dev"
Requires-Dist: pre-commit>=2.20.0; extra == "dev"
Requires-Dist: sphinx>=5.0.0; extra == "dev"
Requires-Dist: sphinx-rtd-theme>=1.0.0; extra == "dev"
Requires-Dist: jupyter>=1.0.0; extra == "dev"
Requires-Dist: ipykernel>=6.0.0; extra == "dev"
Provides-Extra: docs
Requires-Dist: sphinx>=5.0.0; extra == "docs"
Requires-Dist: sphinx-rtd-theme>=1.0.0; extra == "docs"
Requires-Dist: myst-parser>=0.18.0; extra == "docs"
Requires-Dist: sphinx-autodoc-typehints>=1.19.0; extra == "docs"
Provides-Extra: examples
Requires-Dist: jupyter>=1.0.0; extra == "examples"
Requires-Dist: ipykernel>=6.0.0; extra == "examples"
Requires-Dist: openml>=0.12.0; extra == "examples"
Dynamic: license-file
